mehdashti_cache/__init__.py
mehdashti_cache/base.py
mehdashti_cache/decorators.py
mehdashti_cache/memory.py
mehdashti_cache/redis.py
mehdashti_cache-0.1.0.dist-info/METADATA
mehdashti_cache-0.1.0.dist-info/WHEEL
mehdashti_cache-0.1.0.dist-info/RECORD
