Metadata-Version: 2.4
Name: mehdashti-cache
Version: 0.1.0
Summary: Caching utilities with Redis and Memory providers for Smart Platform
Project-URL: Homepage, https://github.com/mehdashti/smart-platform
Project-URL: Repository, https://github.com/mehdashti/smart-platform
Project-URL: Issues, https://github.com/mehdashti/smart-platform/issues
Author-email: mehdashti <mehdashti@gmail.com>
License: MIT
Keywords: cache,fastapi,redis,smart-platform
Classifier: Development Status :: 4 - Beta
Classifier: Framework :: FastAPI
Classifier: Intended Audience :: Developers
Classifier: License :: OSI Approved :: MIT License
Classifier: Programming Language :: Python :: 3
Classifier: Programming Language :: Python :: 3.13
Requires-Python: >=3.13
Requires-Dist: pydantic>=2.0.0
Requires-Dist: redis>=5.0.0
Provides-Extra: dev
Requires-Dist: mypy>=1.0.0; extra == 'dev'
Requires-Dist: pytest-asyncio>=0.21.0; extra == 'dev'
Requires-Dist: pytest-cov>=4.0.0; extra == 'dev'
Requires-Dist: pytest>=7.0.0; extra == 'dev'
Requires-Dist: ruff>=0.1.0; extra == 'dev'
